.DS_Store
src/colors.py
src/weather.py
weathernow-0.1.data/scripts/colors.py
weathernow-0.1.data/scripts/weather.py
weathernow-0.1.dist-info/DESCRIPTION.rst
weathernow-0.1.dist-info/METADATA
weathernow-0.1.dist-info/RECORD
weathernow-0.1.dist-info/WHEEL
weathernow-0.1.dist-info/metadata.json
weathernow-0.1.dist-info/top_level.txt
