Metadata-Version: 2.0
Name: weathernow
Version: 0.1
Summary: terminal weather script
Home-page: UNKNOWN
Author: UNKNOWN
Author-email: UNKNOWN
License: UNKNOWN
Platform: UNKNOWN
